gapprox/__init__.py
gapprox/approximators.py
gapprox/ast_to_dag_visitor.py
gapprox/collapsers.py
gapprox/constants.py
gapprox/count.py
gapprox/dag.py
gapprox/dag2.py
gapprox/errors.py
gapprox/expression.py
gapprox/function.py
gapprox/misc.py
gapprox/objectives.py
gapprox/operator_dict.py
gapprox/operators.py
gapprox/parser.py
gapprox/plotters.py
gapprox/rewarders.py
gapprox/sampler.py
gapprox/symbol.py
gapprox/visitors.py
gapprox-0.4.0.dist-info/licenses/LICENSE
gapprox-0.4.0.dist-info/METADATA
gapprox-0.4.0.dist-info/WHEEL
gapprox-0.4.0.dist-info/top_level.txt
gapprox-0.4.0.dist-info/RECORD
