Metadata-Version: 2.4
Name: gapprox
Version: 0.4.0
Summary: toolkit to find the approximate function of a graph
Author-email: deftasparagusanaconda <deftasparagusanaconda@gmail.com>, Jeffrin Santon <jeffrinsanton0909@gmail.com>
License-Expression: GPL-3.0-or-later
Project-URL: Homepage, https://github.com/deftasparagusanaconda/gapprox
Project-URL: Issues, https://github.com/deftasparagusanaconda/gapprox/issues
Project-URL: Documentation, https://github.com/deftasparagusanaconda/gapprox/documentation
Project-URL: Repository, https://github.com/deftasparagusanaconda/gapprox
Keywords: graph,model,curve,line,parabola,expression,approximation,symbolic,regression,regress,optimization,optimize,iterative,plot
Classifier: Programming Language :: Python :: 3.13
Requires-Python: >=3.11.0
License-File: LICENSE
Requires-Dist: numpy
Requires-Dist: matplotlib
Requires-Dist: networkx
Dynamic: license-file
